hama/__init__.py
hama/g2p.py
hama/jamo.py
hama-1.1.0.dist-info/METADATA
hama-1.1.0.dist-info/WHEEL
hama-1.1.0.dist-info/top_level.txt
hama-1.1.0.dist-info/RECORD
